[{"Instructions":"Just use this one column","Intro_Text":"Hi, we are the Hernandez Family, Independent Baptist Missionaries to Thailand.We arrived in Thailand in December 2014.","Family_Photo":[{"id":"attlny2bLyyeO4Goq","url":"https://dl.airtable.com/PTfzAXLoTYq1BLg6pc2W_familyphoto.png","filename":"familyphoto.png","size":200297,"type":"image/png","thumbnails":{"small":{"url":"https://dl.airtable.com/8XjHbofgRwyVGzpo7xHF_small_familyphoto.png","width":65,"height":36},"large":{"url":"https://dl.airtable.com/4Slzc228Q9uWrp1Ko2dc_large_familyphoto.png","width":467,"height":258}}}]}]
